odoo8_addon_base_partner_sequence-8.0.1.1.1.99.dev9-py2.7-nspkg.pth
odoo8_addon_base_partner_sequence-8.0.1.1.1.99.dev9.dist-info/METADATA
odoo8_addon_base_partner_sequence-8.0.1.1.1.99.dev9.dist-info/RECORD
odoo8_addon_base_partner_sequence-8.0.1.1.1.99.dev9.dist-info/WHEEL
odoo8_addon_base_partner_sequence-8.0.1.1.1.99.dev9.dist-info/namespace_packages.txt
odoo8_addon_base_partner_sequence-8.0.1.1.1.99.dev9.dist-info/top_level.txt
odoo_addons/base_partner_sequence/README.rst
odoo_addons/base_partner_sequence/__init__.py
odoo_addons/base_partner_sequence/__openerp__.py
odoo_addons/base_partner_sequence/data/partner_sequence.xml
odoo_addons/base_partner_sequence/i18n/base_partner_sequence.pot
odoo_addons/base_partner_sequence/i18n/de.po
odoo_addons/base_partner_sequence/i18n/es.po
odoo_addons/base_partner_sequence/i18n/eu.po
odoo_addons/base_partner_sequence/i18n/fi.po
odoo_addons/base_partner_sequence/i18n/fr.po
odoo_addons/base_partner_sequence/i18n/it.po
odoo_addons/base_partner_sequence/i18n/nl.po
odoo_addons/base_partner_sequence/i18n/pt_BR.po
odoo_addons/base_partner_sequence/i18n/sl.po
odoo_addons/base_partner_sequence/models/__init__.py
odoo_addons/base_partner_sequence/models/partner.py
odoo_addons/base_partner_sequence/static/description/icon.png
odoo_addons/base_partner_sequence/tests/__init__.py
odoo_addons/base_partner_sequence/tests/test_base_partner_sequence.py
odoo_addons/base_partner_sequence/views/partner_view.xml
