Metadata-Version: 2.1
Name: odoo8-addon-base-partner-sequence
Version: 8.0.1.1.1.99.dev9
Summary: Sets customer's code from a sequence
Home-page: http://www.initos.com
Author: Tiny/initOS GmbH & Co. KG,ACSONE SA/NV,Odoo Community Association (OCA)
Author-email: support@odoo-community.org
License: AGPL-3
Platform: UNKNOWN
Classifier: Programming Language :: Python
Classifier: Framework :: Odoo
Classifier: License :: OSI Approved :: GNU Affero General Public License v3
Requires-Python: ~=2.7
Requires-Dist: odoo (<9.0a,>=8.0a)
